scematicsapp/__init__.py
scematicsapp/cli.py
scematicsapp/custom_upload.py
scematicsapp/direct_upload.py
scematicsapp/folder_uploads.py
scematicsapp/tag_uploads.py
scematicsapp-0.1.0.dev3.dist-info/METADATA
scematicsapp-0.1.0.dev3.dist-info/WHEEL
scematicsapp-0.1.0.dev3.dist-info/entry_points.txt
scematicsapp-0.1.0.dev3.dist-info/top_level.txt
scematicsapp-0.1.0.dev3.dist-info/RECORD
