Metadata-Version: 2.4
Name: scematicsapp
Version: 0.1.0.dev3
Summary: A CLI tool for managing file uploads
Home-page: https://github.com/scematicsapp
Author: scematics.io
Author-email: karthickeyan@scematics.xyz
Classifier: Programming Language :: Python :: 3
Classifier: License :: OSI Approved :: MIT License
Classifier: Operating System :: OS Independent
Requires-Python: >=3.6
Requires-Dist: typer
Requires-Dist: requests
Requires-Dist: rich
Requires-Dist: pillow
Requires-Dist: opencv-python
Requires-Dist: pathlib
Dynamic: author
Dynamic: author-email
Dynamic: classifier
Dynamic: description
Dynamic: description-content-type
Dynamic: home-page
Dynamic: requires-dist
Dynamic: requires-python
Dynamic: summary
